{"id":"361","slug":"der-unsichtbare-dritte","title":"The Invisible Third","level":"C1","category":"story","sentences":[{"de":"In jedem Gespräch gibt es eine dritte Person, die nicht anwesend ist.","en":"In every conversation there is a third person who is not present."},{"de":"Sie ist die Vergangenheit des Sprechenden, die seine Worte unsichtbar formt.","en":"It is the past of the speaker, which invisibly shapes their words."},{"de":"Als Mira sagte: Ich vertraue niemandem, meinte sie in Wirklichkeit: Ich wurde verletzt.","en":"When Mira said: I trust no one, she really meant: I was hurt."},{"de":"Der gute Zuhörer hört nicht nur, was gesagt wird, sondern auch, was nicht gesagt werden kann.","en":"The good listener hears not only what is said, but also what cannot be said."},{"de":"Sprache ist immer eine Übersetzung aus einem Innenleben, das nie vollständig übertragbar ist.","en":"Language is always a translation from an inner life that can never be fully conveyed."},{"de":"Verstehen bedeutet deshalb nicht, die Worte zu hören – sondern die Person dahinter.","en":"Understanding therefore means not hearing the words – but the person behind them."}],"vocabulary":[{"word":"anwesend","type":"adjective","level":"B1","meaning":"present, in attendance"},{"word":"das Innenleben","article":"das","type":"noun","level":"C1","meaning":"inner life"},{"word":"übertragbar","type":"adjective","level":"C1","meaning":"transferable, conveyable"},{"word":"unsichtbar","type":"adjective","level":"B1","meaning":"invisible"},{"word":"vertrauen","type":"verb","level":"A2","meaning":"to trust"}]}
