{"id":"468","slug":"schwarze-loecher","title":"Black Holes","level":"B2","category":"science","sentences":[{"de":"Ein schwarzes Loch entsteht, wenn ein massereicher Stern am Ende seines Lebens kollabiert.","en":"A black hole forms when a massive star collapses at the end of its life."},{"de":"Die Schwerkraft wird so stark, dass nichts entkommen kann – nicht einmal Licht.","en":"Gravity becomes so strong that nothing can escape – not even light."},{"de":"Die Grenze, jenseits derer keine Rückkehr möglich ist, nennt man Ereignishorizont.","en":"The boundary beyond which no return is possible is called the event horizon."},{"de":"Stephen Hawking entdeckte, dass schwarze Löcher dennoch Strahlung abgeben können.","en":"Stephen Hawking discovered that black holes can nevertheless emit radiation."},{"de":"Diese sogenannte Hawking-Strahlung bedeutet, dass schwarze Löcher langsam verdampfen.","en":"This so-called Hawking radiation means that black holes slowly evaporate."},{"de":"Was mit den Informationen passiert, die sie verschlucken, ist bis heute ungeklärt.","en":"What happens to the information they swallow remains unresolved to this day."}],"vocabulary":[{"word":"massereicher Stern","type":"expression","level":"B2","meaning":"massive star (with large mass)"},{"word":"kollabieren","type":"verb","level":"C1","meaning":"to collapse"},{"word":"der Ereignishorizont","article":"der","type":"noun","level":"C1","meaning":"event horizon"},{"word":"verdampfen","type":"verb","level":"B2","meaning":"to evaporate, to vaporise"},{"word":"ungeklärt","type":"adjective","level":"B2","meaning":"unresolved, unclear"}]}