{"id":"59","slug":"warum-ich-den-herbst-liebe","title":"Why I Love Autumn","level":"A1","category":"blog","sentences":[{"de":"Meine Lieblingszeit ist der Herbst.","en":"My favourite time is autumn."},{"de":"Die Blätter werden rot, orange und gelb.","en":"The leaves turn red, orange and yellow."},{"de":"Die Luft ist frisch und kühl.","en":"The air is fresh and cool."},{"de":"Ich gehe gern mit meinem Hund im Wald spazieren.","en":"I like going for walks in the forest with my dog."},{"de":"Man kann Kastanien und Pilze sammeln.","en":"You can collect chestnuts and mushrooms."},{"de":"Herbst ist einfach wunderschön.","en":"Autumn is simply beautiful."}],"vocabulary":[{"word":"das Blatt","article":"das","type":"noun","level":"A1","meaning":"leaf; sheet (of paper)"},{"word":"die Luft","article":"die","type":"noun","level":"A1","meaning":"air"},{"word":"kühl","type":"adjective","level":"A1","meaning":"cool"},{"word":"die Kastanie","article":"die","type":"noun","level":"A2","meaning":"chestnut"},{"word":"der Pilz","article":"der","type":"noun","level":"A2","meaning":"mushroom; fungus"}]}